{
    "sourceFile": "app/Http/Controllers/ProductController.php",
    "activeCommit": 0,
    "commits": [
        {
            "activePatchIndex": 1,
            "patches": [
                {
                    "date": 1729129368270,
                    "content": "Index: \n===================================================================\n--- \n+++ \n"
                },
                {
                    "date": 1729129378176,
                    "content": "Index: \n===================================================================\n--- \n+++ \n@@ -10,9 +10,9 @@\n      * Display a listing of the resource.\n      */\n     public function index()\n     {\n-\n+        return view('admin.product.index');\n     }\n \n     /**\n      * Show the form for creating a new resource.\n"
                }
            ],
            "date": 1729129368270,
            "name": "Commit-0",
            "content": "<?php\n\nnamespace App\\Http\\Controllers;\n\nuse Illuminate\\Http\\Request;\n\nclass ProductController extends Controller\n{\n    /**\n     * Display a listing of the resource.\n     */\n    public function index()\n    {\n        \n    }\n\n    /**\n     * Show the form for creating a new resource.\n     */\n    public function create()\n    {\n        //\n    }\n\n    /**\n     * Store a newly created resource in storage.\n     */\n    public function store(Request $request)\n    {\n        //\n    }\n\n    /**\n     * Display the specified resource.\n     */\n    public function show(string $id)\n    {\n        //\n    }\n\n    /**\n     * Show the form for editing the specified resource.\n     */\n    public function edit(string $id)\n    {\n        //\n    }\n\n    /**\n     * Update the specified resource in storage.\n     */\n    public function update(Request $request, string $id)\n    {\n        //\n    }\n\n    /**\n     * Remove the specified resource from storage.\n     */\n    public function destroy(string $id)\n    {\n        //\n    }\n}"
        }
    ]
}